sa_metameta/__init__.py
sa_metameta/exceptions.py
sa_metameta/asyncmeta/__init__.py
sa_metameta/meta/__init__.py
sa_metameta-0.0.3.dist-info/LICENSE
sa_metameta-0.0.3.dist-info/METADATA
sa_metameta-0.0.3.dist-info/WHEEL
sa_metameta-0.0.3.dist-info/top_level.txt
sa_metameta-0.0.3.dist-info/RECORD
