Metadata-Version: 2.1
Name: sa-metameta
Version: 0.0.3
Summary: Dynamic SQLAlchemy Metadata Reflection of One or More SQLALchemy Engines
Home-page: https://github.com/Red-HAP/sa-metameta
Author: Red Hat, Inc.
Author-email: info@ansible.com
Maintainer: HAP
Maintainer-email: hproctor@redhat.com
License: Apache-2.0
Project-URL: issues, https://github.com/Red-HAP/sa-metameta/issues
Project-URL: wiki, https://github.com/Red-HAP/sa-metameta/wiki
Keywords: SQLALchemy,asyncio,asyncpg
Classifier: Development Status :: 3 - Alpha
Classifier: Intended Audience :: Developers
Classifier: License :: OSI Approved :: Apache Software License
Classifier: Operating System :: OS Independent
Classifier: Programming Language :: Python :: 3.9
Classifier: Programming Language :: Python :: 3.10
Classifier: Programming Language :: Python :: 3.11
Classifier: Topic :: Database
Classifier: Topic :: Software Development :: Libraries :: Python Modules
Requires-Python: >=3.9
License-File: LICENSE
Requires-Dist: sqlalchemy[asyncio] (>=1.4)
